{
  "type": "FeatureCollection",
  "features": [
    {
      "geometry": {
        "coordinates": [
          10.105419,
          44.140619
        ],
        "type": "Point"
      },
      "properties": {
        "ulsp_type": "Sito",
        "Titolo": "Tecchia di Tenerano",
        "Descrizione": "Grotta con ampio e alto ingresso, sviluppo orizzontale digradante all'interno per formazione di un piccolo lago stagionale. Presente una serie di muretti a secco all'ingresso, sull'ampio pianoro utilizzato a bivacco. ",
        "Data": "06-13-2023",
        "Ora": "10:05:16 AM",
        "Sito": "ULS013",
        "Provincia": "Massa Carrara ",
        "Comune": "Fivizzano",
        "Toponimo": "Tenerano",
        "Microtoponimo": "",
        "Altitudine": 554,
        "Strade d'accesso": "sentiero CAI 46",
        "Altri elementi di localizzazione": "Sul versante SW sul torrente Bardinello. ",
        "Tipologia sito": "Frequentazione antropica",
        "Definizione": "Grotta",
        "Cronologia iniziale": "Protostoria (2300-720 a.C.)",
        "Cronologia finale": "Età contemporanea (1789-2000 d.C.)",
        "Reperti ceramici": "SI",
        "Reperti geologici": "NO",
        "Reperti organici": "NO",
        "Altri manufatti": "da ricognizione: ceramica invetriata, graffita e ceramica di Montelupo",
        "Sicurezza": "accesso in sicurezza",
        "Accessibilità": "Facile",
        "Copertura rete mobile": "Assente",
        "Copertura GPS": "Completa",
        "Foto": "",
        "Link": "",
        "Bibliografia": "",
        "Strumento": "",
        "_umap_options": {
          "popupTemplate": "Default"
        }
      },
      "type": "Feature"
    }
  ]
}